{
    "header": [
        {
            "name": "id",
            "title": "ID",
            "size": 50,
            "sortable": "true",
            "sortDir": "asc",
            "format": "number"
        },
        {
            "name": "name",
            "title": "Name",
            "sortable": "true"
        }
    ],
    "data": [
        [
            1,
            "<button>3 Golden Oldies # 3</button>"
        ],
        [
            2,
            "3 Golden Oldies # 4"
        ],
        [
            3,
            "3 Golden Oldies # 5"
        ],
        [
            4,
            "3 Golden Oldies # 6"
        ],
        [
            5,
            "3 Golden Oldies # 7"
        ],
        [
            6,
            "3 Golden Oldies #1"
        ],
        [
            7,
            "Mac DeMarco - Salad Days (Live on KEXP @Pickathon).mp4"
        ],
        [
            8,
            "Metallica - One (Official Music Video)"
        ],
        [
            9,
            "Pantera - Domination (Official Live Video)"
        ],
        [
            10,
            "Sioux - Suerte"
        ],
        [
            11,
            "The Growlers - One Million Lovers"
        ],
        [
            12,
            "Ballad Of A Teenage Queen ~ Johnny Cash (1957)"
        ],
        [
            13,
            "Band Of Gold ~ Kit Carson  (1955)"
        ],
        [
            14,
            "Between A Kiss And A Sigh ~ Artie Shaw & His Orchestra (1938)"
        ],
        [
            15,
            "Big River ~ Johnny Cash (1957)"
        ],
        [
            16,
            "Blur - Girls And Boys"
        ],
        [
            17,
            "Bobby Garrett - Rose City Chimes - From the cassette album - 'Thumbs Up'"
        ],
        [
            18,
            "Breathless ~ Jerry Lee Lewis (1958)"
        ],
        [
            19,
            "Brenda Lee ~ Les 'Carrot Top' Anderson (1958) (Country & Western)"
        ],
        [
            20,
            "Bronski Beat - Smalltown Boy ( Extreme Long Version)"
        ],
        [
            21,
            "Bublitchki ~ Ziggy Elman & His Orchestra (1938)"
        ],
        [
            22,
            "David Bowie Starman (1972) official video"
        ],
        [
            23,
            "La Polla Records - Ellos Dicen Mierda"
        ],
        [
            24,
            "New Order - Blue Monday (Official Lyric Video)"
        ],
        [
            25,
            "Pantera - Walk (Official Music Video)"
        ],
        [
            26,
            "Sonrie y Lucha - La Familia Iskariote"
        ],
        [
            27,
            "Buck Owens and the Buckaroos Live At Caregie Hall 1966 - Side #1"
        ],
        [
            28,
            "Buck Owens and the Buckaroos Live At Caregie Hall 1966 - Side #2"
        ],
        [
            29,
            "Bud Isaacs - Bud's Bounce"
        ],
        [
            30,
            "CARL BUTLER -   JEALOUS HEART"
        ],
        [
            31,
            "Caifanes - No Dejes Qu\u00e9... ((Cover Audio)(Video))"
        ],
        [
            32,
            "Charley Pride - The Snakes Crawl At Night"
        ],
        [
            33,
            "Chicano Batman - Freedom Is Free (Official Video)"
        ],
        [
            34,
            "Claptone - Dear Life ft. Jaw (FULL EP) _ TSTLM"
        ],
        [
            35,
            "Comes Love ~ Artie Shaw & His Orchestra (1939)"
        ],
        [
            36,
            "Cool Love ~ Wanda Jackson  (1957)"
        ],
        [
            37,
            "Quisiera ser Alcohol - Caifanes"
        ],
        [
            38,
            "Cool Time (In The Old Town Tonight) ~ Bob Crewe (1960)"
        ],
        [
            39,
            "Daddy's Boy ~ Glen Gray & The Casa Loma Orchestra (1938)"
        ],
        [
            40,
            "Days of Lavender"
        ],
        [
            41,
            "De La Ausencia Y De Ti"
        ],
        [
            42,
            "Doc Watson - Mama Don't Allow No Music"
        ],
        [
            43,
            "Down In Mexico ~ Ella Mae Morse (1956) Capitol # F3387"
        ],
        [
            44,
            "Echo & The Bunnymen - The Killing Moon (Official Music Video)"
        ],
        [
            45,
            "Edna ~ The Medallions (1955)(78 rpm)"
        ],
        [
            46,
            "El Paso ~ Marty Robbins (1959)"
        ],
        [
            47,
            "Elton John - Bennie And The Jets (Official Music Video)"
        ],
        [
            48,
            "Kaos Etiliko- Hoy es mi Dia (Sale el sol)"
        ],
        [
            49,
            "Sin Dios - Sistema de ense\u00f1anza"
        ],
        [
            50,
            "The Black Keys - Tighten Up [Official Music Video]"
        ],
        [
            51,
            "White Zombie ft. Iggy Pop - Black Sunshine (Official Video)"
        ],
        [
            52,
            "Elton John - Don't Go Breaking My Heart (with Kiki Dee)"
        ],
        [
            53,
            "Elton John - Rocket Man (Official Music Video)"
        ],
        [
            54,
            "Elton John - Tiny Dancer (Official Music Video)"
        ],
        [
            55,
            "Ever Lovin' Fingers ~ Jimmy Bowen w_ The Rhythm Orchids (1957)"
        ],
        [
            56,
            "FOALS - Birch Tree [Official Music Video]"
        ],
        [
            57,
            "FOALS - Into The Surf [Official Music Video]"
        ],
        [
            58,
            "Franc Moody - Skin on Skin (Official Audio)"
        ],
        [
            59,
            "Franc Moody - Terra Firma"
        ],
        [
            60,
            "Gorillaz - Andromeda (Purple Disco Machine Remix)"
        ],
        [
            61,
            "Greta Van Fleet - Edge Of Darkness (Live in Toronto _ 2018)"
        ],
        [
            62,
            "New Order - Temptation (Official Music Video)"
        ],
        [
            63,
            "Pantera - I'm Broken (Official Music Video)"
        ],
        [
            64,
            "White Zombie - More Human Than Human (Official Video)"
        ],
        [
            65,
            "Caf\u00e9 Tacvba - Una Ma\u00f1ana [Mtv Unplugged] [480p]"
        ],
        [
            66,
            "Harlem Nocturne ~ Jay White  (1958)"
        ],
        [
            67,
            "Have A Good Time ~ Sue Thompson (1962)"
        ],
        [
            68,
            "He's My Guy ~ Harry James & His Orchestra (1942)"
        ],
        [
            69,
            "I'm Here To Tell You ~ Jerry Foster (1959)"
        ],
        [
            70,
            "I'm Stickin' With You ~ Jimmy Bowen w_ The Rhythm Orchids (1957)"
        ],
        [
            71,
            "If I Were Sure Of You ~ Bob Crosby & HIs Orchestra (1939)"
        ],
        [
            72,
            "If The Boy Only Knew ~ Sue Thompson (1962)"
        ],
        [
            73,
            "In The Heart Of A Fool ~ Johnnie Ray  (1960)"
        ],
        [
            74,
            "In The Mood ~ Ernie Fields & His Orchestra  (1960)"
        ],
        [
            75,
            "It's Been A Long Time"
        ],
        [
            76,
            "Piperrak-Kualkier dia"
        ],
        [
            77,
            "White Zombie - Thunder Kiss '65 (Official Video)"
        ],
        [
            78,
            "It's My House - DIANA ROSS '1979"
        ],
        [
            79,
            "It's Twelve Thirty-Five ~ Sue Thompson (1963)"
        ],
        [
            80,
            "Jim James - A New Life"
        ],
        [
            81,
            "Jim James, Teddy Abrams, Louisville Orchestra - Back To The End Of The World (Visualizer)"
        ],
        [
            82,
            "Jim James, Teddy Abrams, Louisville Orchestra - Back To The End Of The World"
        ],
        [
            83,
            "Jim James, Teddy Abrams, Louisville Orchestra - Set It To Song"
        ],
        [
            84,
            "Just As Though You Were Here ~ Tommy Dorsey & His Orchestra (1942)"
        ],
        [
            85,
            "KOLLEKTIV TURMSTRASSE - Sorry I Am Late (Official Video)"
        ],
        [
            86,
            "Kraftwerk - The Model"
        ],
        [
            87,
            "Laid Back  - Bakerman Original Video"
        ],
        [
            88,
            "White Zombie - Welcome To Planet M.F."
        ],
        [
            89,
            "'Let 'Em In' - PaulMcCartney.com Track of the Week"
        ],
        [
            90,
            "L'Imp\u00e9ratrice 'Agitations Tropicales'"
        ],
        [
            91,
            "L'Imp\u00e9ratrice \u2014 SONATE PACIFIQUE"
        ],
        [
            92,
            "Laid Back - Brother"
        ],
        [
            93,
            "Laid Back - Don't Shoot The Sun Down (Iive)"
        ],
        [
            94,
            "Laid Back - Enjoy the Vibes"
        ],
        [
            95,
            "Laid Back - Highway Of Love"
        ],
        [
            96,
            "Laid Back - Sunshine Reggae"
        ],
        [
            97,
            "Laid Back - White Horse [Official Music Video]"
        ],
        [
            98,
            "Like A Baby ~ Toni Arden  (1957)"
        ],
        [
            99,
            "Fools Paradise by Buddy Holly.mp4"
        ],
        [
            100,
            "L'Imp\u00e9ratrice \u2657 VANILLE FRAISE"
        ],
        [
            101,
            "L'Imp\u00e9ratrice \u2657 VOODOO (Live)"
        ],
        [
            102,
            "Lloyd Green - Ride Ride Ride"
        ],
        [
            103,
            "Lloyd Green - Show Me The Way To The Circus"
        ],
        [
            104,
            "Love Is All We Need ~ Tommy Edwards (1958) (w_ echo)"
        ],
        [
            105,
            "Love Me Again ~ The Rover Boys (1955)"
        ],
        [
            106,
            "Mac Wiseman - Johnny's Cash and Charley's Pride"
        ],
        [
            107,
            "Mama, Don't Cry At My Wedding ~ Sue Thompson (1964)"
        ],
        [
            108,
            "Mariya Takeuchi \u7af9\u5185 \u307e\u308a\u3084 Plastic Love"
        ],
        [
            109,
            "Matthew Wilder - Break My Stride ( Full & HQ )"
        ],
        [
            110,
            "Pantera - Cemetery Gates (Official Music Video)"
        ],
        [
            111,
            "Sin Dios La hoguera de la revoluci\u00f3n"
        ],
        [
            112,
            "D\u00edas y Flores"
        ],
        [
            113,
            "Keane - Everybody's Changing (Official Video)"
        ],
        [
            114,
            "Moby 'In This World' - Official video"
        ],
        [
            115,
            "Moby - Extreme Ways"
        ],
        [
            116,
            "Moby - Natural Blues"
        ],
        [
            117,
            "Moby - Why Does My Heart Feel So Bad"
        ],
        [
            118,
            "My Morning Jacket    Phone Went West    Red Rocks August 4, 2012"
        ],
        [
            119,
            "My Morning Jacket - Circuital (Sub. Espanol)"
        ],
        [
            120,
            "My Morning Jacket - Rocket Man (Subtitulada en Espa\u00f1ol)"
        ],
        [
            121,
            "Oh Lonesome Me ~ Don Gibson (1957)"
        ],
        [
            122,
            "Pass The Koutchie"
        ],
        [
            123,
            "Phats & Small - Turn Around (Official Music Video)"
        ],
        [
            124,
            "Sinergia - H\u00e1galo Bien [HD]"
        ],
        [
            125,
            "A Letter To An Angel ~ Jimmy Clanton (1958)"
        ],
        [
            126,
            "A Part Of Me ~ Jimmy Clanton (1958)"
        ],
        [
            127,
            "A Pink Cocktail For A Blue Lady ~ Glenn Miller & His Orchestra (1942)"
        ],
        [
            128,
            "A Sinner Kissed An Angel ~ Bob Crosby & His Orchestra (1941)"
        ],
        [
            129,
            "A White Sport Coat ~ Marty Robbins (1957)"
        ],
        [
            130,
            "AFI -  Cure Icon Live -  Just like Heaven"
        ],
        [
            131,
            "Alice In Chains - Would (Official HD Video)"
        ],
        [
            132,
            "And The Angels Sing ~ Ziggy Elman & His Orchestra (1938)"
        ],
        [
            133,
            "Arcade Fire - Intervention"
        ],
        [
            134,
            "Arcade Fire - Song on the Beach; Photograph"
        ],
        [
            135,
            "06Chuck Mangione-Consuelos Love Theme (cd1) part1.mp4"
        ],
        [
            136,
            "A Chain Of Flowers"
        ],
        [
            137,
            "Absynthe Minded - Envoi"
        ],
        [
            138,
            "Te He Dejado De Querer - Conjunto Primavera.mp4"
        ],
        [
            139,
            "A Flock Of Seagulls - Space Age Love Song 1982.mp4"
        ],
        [
            140,
            "AFI -  Cure Icon Live -  Just like Heaven.mp4"
        ],
        [
            141,
            "AFI-Cure_Icon_Live-Just_like_Heaven.mp4"
        ],
        [
            142,
            "Adonais"
        ],
        [
            143,
            "A Flor De Piel"
        ],
        [
            144,
            "A Forest - (Feat. Earl Slick, unreleased 2001)"
        ],
        [
            145,
            "Agitations tropicales.mp4"
        ],
        [
            146,
            "Alice In Chains - Down in a Hole (MTV Unplugged - HD Video)"
        ],
        [
            147,
            "Alpha Blondy - Banana.mp4"
        ],
        [
            148,
            "Amour plastique.mp4"
        ],
        [
            149,
            "And You And I in HD by Yes.mp4"
        ],
        [
            150,
            "4 Non Blondes - What's Up (Official Video)"
        ],
        [
            151,
            "Alice In Chains - Rooster (Official HD Video)"
        ],
        [
            152,
            "Plaid And Calico ~ Johnny Horton  (1959)"
        ],
        [
            153,
            "Pulp - Common People (Official Video)"
        ],
        [
            154,
            "Quite A Picture ~ Bob Crewe (1960)"
        ],
        [
            155,
            "Ray Conniff and Julio Iglesias - 'Hey!'"
        ],
        [
            156,
            "Red Foley - Hot Toddy"
        ],
        [
            157,
            "Sara Ruth ~ Mike Smith  (1959)"
        ],
        [
            158,
            "Soda Stereo - Estoy Azulado (Official Audio)"
        ],
        [
            159,
            "Speedy Gonzalez ~ Mindy Carson (1954)"
        ],
        [
            160,
            "Stonewall Jackson - B.J. The D.J. 1964"
        ],
        [
            161,
            "Street Scene ~ Jay White  (1958)"
        ],
        [
            162,
            "Audioslave - Show Me How to Live (Official Video)"
        ],
        [
            163,
            "Babble"
        ],
        [
            164,
            "Bain.mp4"
        ],
        [
            165,
            "Balance ton quoi.mp4"
        ],
        [
            166,
            "Black Uhuru - The Great Train Robbery (Dance Mix).mp4"
        ],
        [
            167,
            "Blitz - New Age - (UKDK UK 1983).mp4"
        ],
        [
            168,
            "Blur "
        ],
        [
            169,
            "Bobby Vee  - Take Good Care Of My Baby  - 1961.mp4"
        ],
        [
            170,
            "Breathe"
        ],
        [
            171,
            "Te Me Olvidaste-Marco Antonio Solis-2010.mp4"
        ],
        [
            172,
            "Audioslave - I Am The Highway"
        ],
        [
            173,
            "Audioslave - Like a Stone (Official Video)"
        ],
        [
            174,
            "Baby Ill Be Yours - The Gaylads (Subtitulos Espa\u00f1ol).mp4"
        ],
        [
            175,
            "Tatsuro Yamashita - Magic Ways"
        ],
        [
            176,
            "The Bucketheads - The Bomb [These Sounds Fall Into My Mind] (Official Video)"
        ],
        [
            177,
            "The Chemical Brothers - Another World (Official Music Video)"
        ],
        [
            178,
            "The Chemical Brothers - Get Yourself High"
        ],
        [
            179,
            "The Chemical Brothers - Star Guitar (Official Music Video)"
        ],
        [
            180,
            "The Chemical Brothers - Wide Open ft. Beck (Official Music Video)"
        ],
        [
            181,
            "The Chemical Brothers - Wide Open ft. Beck [8D AUDIO]"
        ],
        [
            182,
            "The Cure (extended) To The Sky"
        ],
        [
            183,
            "The Cure - Halo with lyrics and subs"
        ],
        [
            184,
            "The Funk Phenomena"
        ],
        [
            185,
            "Arcade Fire - Song on the Beach Photograph.mp4"
        ],
        [
            186,
            "Artifical Red"
        ],
        [
            187,
            "Audioslave - Be Yourself (Album Version, Closed Captioned)"
        ],
        [
            188,
            "'Cause I Ask You To ~ Sue Thompson (1963)"
        ],
        [
            189,
            "Did You Miss Me  ~ Wanda Jackson  (1957)"
        ],
        [
            190,
            "Don't Look Now ~ Larry Clinton & His Orchestra (1939)"
        ],
        [
            191,
            "If I Could See The World (Through The Eyes Of A Child) ~ Patsy Cline (1964) (Country & Western)"
        ],
        [
            192,
            "Never Love Again ~ Sue Thompson (1961)"
        ],
        [
            193,
            "Now You Know (I Love You So) ~ The Channels (1956)(78 rpm)"
        ],
        [
            194,
            "Over The Rainbow ~ Jay White  (1958)"
        ],
        [
            195,
            "Sea of Heartbreak"
        ],
        [
            196,
            "Self Revolution.mp4"
        ],
        [
            197,
            "Talk Of The School ~ Sonny James (1959)"
        ],
        [
            198,
            "Unchained Melody ~ The Browns (1959)"
        ],
        [
            199,
            "Bee Gees - Night Fever (Official Music Video)"
        ],
        [
            200,
            "Conjunto Primavera - Vuelve Conmigo.mp4"
        ],
        [
            201,
            "Creedence Clearwater Revival - Have You Ever Seen The Rain (Official)"
        ],
        [
            202,
            "Crowded House - Don't Dream It's Over (Official Music Video)"
        ],
        [
            203,
            "De La Ausencia Y De Ti.mp4"
        ],
        [
            204,
            "Nirvana - The Man Who Sold The World (MTV Unplugged).mp4"
        ],
        [
            205,
            "CONJUNTO PRIMAVERA NO SE DECIRTE ADIOS.mp4"
        ],
        [
            206,
            "Conjunto Primavera - Perdoname Mi Amor.mp4"
        ],
        [
            207,
            "Conjunto Primavera - quien como tu (cover).mp4"
        ],
        [
            208,
            "Crash Test Dummies - Mmm Mmm Mmm Mmm (Official Video)"
        ],
        [
            209,
            "Kraftwerk - Album (The Man Machine) Full"
        ],
        [
            210,
            "LOS BUNKERS  -  LLUEVE SOBRE LA CIUDAD"
        ],
        [
            211,
            "conjunto primavera no le ruegues.mp4"
        ],
        [
            212,
            "Alton Ellis - Rocksteady"
        ],
        [
            213,
            "CONJUNTO PRIMAVERA - Muero.mp4"
        ],
        [
            214,
            "Conjunto Primavera - La Celda 27.mp4"
        ],
        [
            215,
            "Conjunto Primavera - Mi Primera Vez.mp4"
        ],
        [
            216,
            "Conjunto Primavera - Mi destino fue quererte.mp4"
        ],
        [
            217,
            "Conjunto Primavera Mi Mayor Fracaso.mp4"
        ],
        [
            218,
            "Los Amigos Invisibles \u2013 Ponerte en Cuatro (Official Video)"
        ],
        [
            219,
            "Sonido Rebelde"
        ],
        [
            220,
            "conjunto primavera me nortie.mp4"
        ],
        [
            221,
            "Conjunto Primavera - Ave Cautiva (Video Oficial).mp4"
        ],
        [
            222,
            "Conjunto Primavera - Senti.mp4"
        ],
        [
            223,
            "Conjunto Primavera - Te Llor\u00e9.mp4"
        ],
        [
            224,
            "Conjunto Primavera - Una Vez Mas.mp4"
        ],
        [
            225,
            "Soda Stereo - Estoy Azulado (Official Audio).mp4"
        ],
        [
            226,
            "CONJUNTO PRIMAVERA  ECHAME A MI LA CULPA.mp4"
        ],
        [
            227,
            "CONJUNTO PRIMAVERA HAZME OLVIDARLA.mp4"
        ],
        [
            228,
            "Conjunto Primavera   borracho y loco.mp4"
        ],
        [
            229,
            "Conjunto Primavera - Empaca Tus Cosas.mp4"
        ],
        [
            230,
            "Conjunto Primavera En cada gota de mi sangre.mp4"
        ],
        [
            231,
            "MUNICIPAL WASTE - You're Cut Off (OFFICIAL MUSIC VIDEO)"
        ],
        [
            232,
            "My Morning Jacket - Mahgeetah"
        ],
        [
            233,
            "Coldplay - Yellow (Official Video)"
        ],
        [
            234,
            "Coming Up"
        ],
        [
            235,
            "La Zona del Terror"
        ],
        [
            236,
            "Chris Cornell  - 'Nothing Compares 2 U' (Prince Cover) [Live @ SiriusXM] _ Lithium"
        ],
        [
            237,
            "Claptone - Dear Life ft Jaw (FULL EP)  TSTLM.mp4"
        ],
        [
            238,
            "Pixies - Where Is My Mind"
        ],
        [
            239,
            "The Growlers - .mp4"
        ],
        [
            240,
            "Vampire Weekend - Oxford Comma.mp4"
        ],
        [
            241,
            "ALL SHALL PERISH - Eradication (OFFICIAL MUSIC VIDEO)"
        ],
        [
            242,
            "CASTLEBEAT - VHS (Full Album).mp4"
        ],
        [
            243,
            "Canop\u00e9e.mp4"
        ],
        [
            244,
            "LUIS EDUARDO AUTE - ALEVOSIA"
        ],
        [
            245,
            "Pixies - Wave Of Mutilation (Peel Session)"
        ],
        [
            246,
            "Bronski Beat - Smalltown Boy ( Extreme Long Version).mp4"
        ],
        [
            247,
            "Burn (From The Crow OST)"
        ],
        [
            248,
            "Calypso Rose - Calypso Queen (Mo Laudi Remix).mp4"
        ],
        [
            249,
            "Desde que te perdi - marco antonio solis.mp4"
        ],
        [
            250,
            "Silvio Rodriguez - Cancion del elegido"
        ],
        [
            251,
            "Don't You Worry Your Pretty Little Head ~ Don Cherry (1957)"
        ],
        [
            252,
            "Earth Angel ~ The Crew Cuts (1955)(78 rpm)"
        ],
        [
            253,
            "Flyte - Light me up"
        ],
        [
            254,
            "Green Day - Basket Case [Official Music Video]"
        ],
        [
            255,
            "Here Lies My Love ~ Mr. Undertaker (1955)(78 rpm)"
        ],
        [
            256,
            "I Can't Afford To Dream ~ Artie Shaw & His Orchestra (1939)"
        ],
        [
            257,
            "I Got A Hole In My Pirogue ~ Johnny Horton  (1956)"
        ],
        [
            258,
            "I Think I'll Go Home And Cry ~ Chuck Reed (1955) (Country & Western)"
        ],
        [
            259,
            "Juke Box ~ Leon McAuliffe  (1965)"
        ],
        [
            260,
            "Nobody But You ~ Dee Clark (1958)(78 rpm)"
        ],
        [
            261,
            "Paper Tiger ~ Sue Thompson (1964)"
        ],
        [
            262,
            "Resistire - Los Muertos De Cristo"
        ],
        [
            263,
            "-My-Kind-of-Woman-OFFICIAL-VIDEO.mp4"
        ],
        [
            264,
            "Franc Moody - Skin on Skin (Official Audio).mp4"
        ],
        [
            265,
            "Franc Moody - Terra Firma.mp4"
        ],
        [
            266,
            "Future Islands - For Sure (Official Video).mp4"
        ],
        [
            267,
            "Jaguares - Fin HD"
        ],
        [
            268,
            "Metallica - Enter Sandman (Official Music Video)"
        ],
        [
            269,
            "Sekta Core - Delfino"
        ],
        [
            270,
            "The Lumineers - Ho Hey (Official Video)"
        ],
        [
            271,
            "FOALS - Birch Tree [Official Music Video].mp4"
        ],
        [
            272,
            "FOALS - Neptune [Official Music Video]"
        ],
        [
            273,
            "La Ley - Mentira (Video Oficial)"
        ],
        [
            274,
            "Limp Bizkit - Nookie (Official Video)"
        ],
        [
            275,
            "Sonic Youth - Kool Thing (Official Music Video)"
        ],
        [
            276,
            "Feng Suave - Honey, There's No Time (Official Music Video)"
        ],
        [
            277,
            "Flora Adams - Fire Fire (Subt\u00edtulos  en Espa\u00f1ol).mp4"
        ],
        [
            278,
            "Flyte - Light me up.mp4"
        ],
        [
            279,
            "Municipal Waste - Wolves of Chernobyl (Official Video)"
        ],
        [
            280,
            "Faith No More - Epic (Official Music Video)"
        ],
        [
            281,
            "Fear Of Ghosts"
        ],
        [
            282,
            "Feels So Good - Chuck Mangione [FULL VERSION].mp4"
        ],
        [
            283,
            "Kinky - Hasta Quemarnos [Official Music Video]"
        ],
        [
            284,
            "Sinergia - Te Enojai Por Todo (Video Oficial)"
        ],
        [
            285,
            "Ska-P - Ni\u00f1o Soldado (Videoclip)"
        ],
        [
            286,
            "The Strokes - Last Nite (Official Music Video)"
        ],
        [
            287,
            "Elton John - Rocket Man (Official Music Video).mp4"
        ],
        [
            288,
            "Estranged"
        ],
        [
            289,
            "Extreme - More Than Words (Official Video)"
        ],
        [
            290,
            "Face to Face - Disconnected.mp4"
        ],
        [
            291,
            "Ska-P - Mis Colegas (Videoclip)"
        ],
        [
            292,
            "Dreams (2004 Remaster)"
        ],
        [
            293,
            "ESPERANZA ETERNA - NATURALEZA RELAJANTE.mp4"
        ],
        [
            294,
            "Elvis Presley - My Way (Aloha From Hawaii, Live in Honolulu, 1973)"
        ],
        [
            295,
            "Epic Beautiful Emotional Uplifting - Life is neverending (visita a Cerati).mp4"
        ],
        [
            296,
            "Kaos Etiliko 'No Hay Agua' (Disco Completo) - 1998 -"
        ],
        [
            297,
            "Los amantes de Lola - Beber de tu sangre"
        ],
        [
            298,
            "Doing The Unstuck"
        ],
        [
            299,
            "Duran Duran - Come Undone (Official Music Video)"
        ],
        [
            300,
            "Metallica - Whiplash"
        ],
        [
            301,
            "Porsupuesto\u0301n"
        ],
        [
            302,
            "\u00c9coute Ch\u00e9rie.mp4"
        ],
        [
            303,
            "Dr Hook -  'Sharing The Night Together' (1978)"
        ],
        [
            304,
            "Dr Hook - 'When You're In Love With A Beautiful Woman'"
        ],
        [
            305,
            "Dredd Song (From Judge Dredd Ost)"
        ],
        [
            306,
            "SLAYER - You Against You (OFFICIAL MUSIC VIDEO)"
        ],
        [
            307,
            "Elton John - Dont Go Breaking My Heart (with Kiki Dee).mp4"
        ],
        [
            308,
            "Diamonds ~ Jimmy Elledge (1962) (w_echo)"
        ],
        [
            309,
            "Going Away To School ~ Warner Mack (1958)"
        ],
        [
            310,
            "I Promise To Remember  ~ Frankie Lymon & The Teenagers (1956)(78 rpm)"
        ],
        [
            311,
            "If I Didn't Care ~ The Hilltoppers (1954)(78 rpm)"
        ],
        [
            312,
            "It Only Happens When I Dance With You ~ Art Lund (1947)"
        ],
        [
            313,
            "Just Married ~ Marty Robbins  (1958)"
        ],
        [
            314,
            "Listen To The Wind ~ Jeanie Johnson (1958)"
        ],
        [
            315,
            "My Baby's Gone, On, On ~ Johnnie & Joe (1957)(78 rpm)"
        ],
        [
            316,
            "Platero y Tu - El roce de tu cuerpo"
        ],
        [
            317,
            "Poor Man's Riches ~ Benny Barnes  (1956)"
        ],
        [
            318,
            "Stairway Of Love ~ Marty Robbins  (1958)"
        ],
        [
            319,
            "Extremoduro - Rojitas las orejas (con letra).mp4"
        ],
        [
            320,
            "Julio Iglesias - De ni\u00f1a a mujer.mp4"
        ],
        [
            321,
            "Julio Iglesias - Hey.mp4"
        ],
        [
            322,
            "Julio Iglesias - La Gota Fr\u00eda.mp4"
        ],
        [
            323,
            "Julio Iglesias - La vida sigue igual.mp4"
        ],
        [
            324,
            "Rage Against The Machine - Know Your Enemy (Audio)"
        ],
        [
            325,
            "Julio Iglesias  -  Como Tu.mp4"
        ],
        [
            326,
            "Julio Iglesias - Baila Morena.mp4"
        ],
        [
            327,
            "Julio Iglesias - Cada Dia Mas.mp4"
        ],
        [
            328,
            "Julio Iglesias - Con la misma piedra.mp4"
        ],
        [
            329,
            "Skid Row - 18 And Life (Official Music Video)"
        ],
        [
            330,
            "Skid Row - Youth Gone Wild (Official Music Video)"
        ],
        [
            331,
            "jULIO iGLESIAS AMANTES.mp4"
        ],
        [
            332,
            "\"Te conozco\", de Silvio Rodr\u00edguez.mp4"
        ],
        [
            333,
            "It Used To Be Me"
        ],
        [
            334,
            "Its Been A Long Time.mp4"
        ],
        [
            335,
            "Jim James Teddy Abrams Louisville Orchestra - Back To The End Of The World (Visualizer).mp4"
        ],
        [
            336,
            "Julio Iglesias - A flor de piel.mp4"
        ],
        [
            337,
            "PLATERO Y TU - Alucinante (Video)"
        ],
        [
            338,
            "Gorillaz - Andromeda (Purple Disco Machine Remix).mp4"
        ],
        [
            339,
            "I Still Haven't Found What I'm Looking For"
        ],
        [
            340,
            "I'm Above"
        ],
        [
            341,
            "INXS - Dont Change.mp4"
        ],
        [
            342,
            "Imagine (Remastered 2010)"
        ],
        [
            343,
            "Irremediablemente - Conjunto Primavera.mp4"
        ],
        [
            344,
            "Ska-P - Lucrecia"
        ],
        [
            345,
            "Hotmood - Superstar.mp4"
        ],
        [
            346,
            "I Can't Help Myself"
        ],
        [
            347,
            "I Don't Wanna Be A Soldier (Live at The Moore)"
        ],
        [
            348,
            "IceCube - Check Yo Self.mp4"
        ],
        [
            349,
            "Primus - Wynona's Big Brown Beaver"
        ],
        [
            350,
            "Skeletons Of Society"
        ],
        [
            351,
            "gracias por estar conmigo conjunto primavera.mp4"
        ],
        [
            352,
            "Give It All You Got.mp4"
        ],
        [
            353,
            "Goo Goo Dolls - Iris [Official Music Video]"
        ],
        [
            354,
            "Honey Claws - Digital Animal"
        ],
        [
            355,
            "How Beautiful You Are"
        ],
        [
            356,
            "Guns N' Roses - Patience"
        ],
        [
            357,
            "Harold And Joe"
        ],
        [
            358,
            "Hermano - Marco Antonio Solis.mp4"
        ],
        [
            359,
            "Hello, I Love You (Unreleased)"
        ],
        [
            360,
            "Limp Bizkit - My Way (Official Video)"
        ],
        [
            361,
            "Los Apson. Anoche me enamor\u00e9"
        ],
        [
            362,
            "Nomas Contigo \u2566 Mario Quintero (con letra)"
        ],
        [
            363,
            "Greta Van Fleet - Edge Of Darkness (Live in Toronto  2018).mp4"
        ],
        [
            364,
            "August Burns Red - Composure (Official Music Video)"
        ],
        [
            365,
            "IDLES - Model Village (Live on KEXP)"
        ],
        [
            366,
            "Peace Sells - Megadeth (original version)"
        ],
        [
            367,
            "Platero y T\u00fa - Si t\u00fa te vas (Videoclip Oficial).mp4"
        ],
        [
            368,
            "Sin Dios -  1936, un pueblo en armas"
        ],
        [
            369,
            "The Good Life - Lovers Need Lawyers [Official Music Video]"
        ],
        [
            370,
            "The Verve - Bitter Sweet Symphony (Official Music Video)"
        ],
        [
            371,
            "Those Who Know ~ Benny Barnes (1956)"
        ],
        [
            372,
            "Thrift Shop (feat. Wanz)"
        ],
        [
            373,
            "Tim Holiday - Feed The Fish"
        ],
        [
            374,
            "U2 - Love Is Bigger Than Anything In Its Way"
        ],
        [
            375,
            "U2 - Three  1979 (Full EP)"
        ],
        [
            376,
            "Webb Pierce - Where'd Ya Stay Last Night"
        ],
        [
            377,
            "Weeping Willow ~ The Five Satins (1956)"
        ],
        [
            378,
            "blink-182 - Always (Official Video)"
        ],
        [
            379,
            "Julio Iglesias - Si me dejas no vale.mp4"
        ],
        [
            380,
            "10_15 Saturday Night"
        ],
        [
            381,
            "2 Late"
        ],
        [
            382,
            "A Few Hours After This ..."
        ],
        [
            383,
            "A Foolish Arrangement"
        ],
        [
            384,
            "A Man Inside My Mouth"
        ],
        [
            385,
            "A Pink Dream"
        ],
        [
            386,
            "All I Have To Do Is Dream - The Everly Brothers -  Lyrics.mp4"
        ],
        [
            387,
            "Another Journey By Train"
        ],
        [
            388,
            "Ch\u00e2teau perdu.mp4"
        ],
        [
            389,
            "Claire Laffut - La fess\u00e9e  Subs Espa\u00f1ol.mp4"
        ],
        [
            390,
            "Conjunto Primavera 10 kilometros.mp4"
        ],
        [
            391,
            "Descent"
        ],
        [
            392,
            "Do The Hansa.mp4"
        ],
        [
            393,
            "Dying Day"
        ],
        [
            394,
            "First Chance I Get ~ Warner Mack (1958)"
        ],
        [
            395,
            "The Big Hand"
        ],
        [
            396,
            "The Chemical Brothers - Wide Open ft Beck (Official Music Video).mp4"
        ],
        [
            397,
            "The D\u00f8 - Anita No! (Live on KEXP)"
        ],
        [
            398,
            "Thin Lizzy - Whiskey In The Jar (official music video)"
        ],
        [
            399,
            "This Is A Lie"
        ],
        [
            400,
            "Young Americans (From 104.9 XFM Compilation)"
        ],
        [
            401,
            "Out Of Mind"
        ],
        [
            402,
            "Pill Box Tales"
        ],
        [
            403,
            "Plastic Passion"
        ],
        [
            404,
            "This Twilight Garden"
        ],
        [
            405,
            "Tired Of Toein' The Line - Rocky Burnette - HQ_HD"
        ],
        [
            406,
            "Toi Et Moi.mp4"
        ],
        [
            407,
            "Tom Petty - Free Fallin'"
        ],
        [
            408,
            "Y QUE ME IMPORTA - CONJUNTO PRIMAVERA.mp4"
        ],
        [
            409,
            "el ultimo beso - los apson"
        ],
        [
            410,
            "DE GOLPE EN GOLPE -CONJUNTO PRIMAVERA-.mp4"
        ],
        [
            411,
            "David Bowie - 'There Is A Happy Land' - 1967"
        ],
        [
            412,
            "David Bowie - 'Uncle Arthur' - 1967"
        ],
        [
            413,
            "David Bowie - 'We Are Hungry Men' - 1967"
        ],
        [
            414,
            "David Bowie - 'When I Live My Dream' - 1967"
        ],
        [
            415,
            "Elvis Presley - Blue Moon (1956)"
        ],
        [
            416,
            "Elvis Presley - Blue Suede Shoes (1956)"
        ],
        [
            417,
            "Elvis Presley - I Got A Woman (1956)"
        ],
        [
            418,
            "Mac-DeMarco--Treat-Her-Better.mp4"
        ],
        [
            419,
            "My Morning Jacket - Golden"
        ],
        [
            420,
            "Platero y tu - Cigarrito.mp4"
        ],
        [
            421,
            "TOOL - Schism"
        ],
        [
            422,
            "Take It Easy (2013 Remaster)"
        ],
        [
            423,
            "To The Sky"
        ],
        [
            424,
            "Tony Orlando - Dont Let Go (Pete Herbert Edit).mp4"
        ],
        [
            425,
            "Your Decision"
        ],
        [
            426,
            "Challenge Of Love ~ Harry Charles (1963)"
        ],
        [
            427,
            "Don Cherry - When You Leave Amarillo (Turn Out the Lights)"
        ],
        [
            428,
            "Elvis Presley - I Love You Because (1956)"
        ],
        [
            429,
            "Elvis Presley - I'll Never Let You Go (1956)"
        ],
        [
            430,
            "Elvis Presley - I'm Counting On You (1956)"
        ],
        [
            431,
            "Elvis Presley - I'm Gonna Sit Right Down And Cry (1956)"
        ],
        [
            432,
            "Elvis Presley - Just Because (1956)"
        ],
        [
            433,
            "Elvis Presley - Money Honey (1956)"
        ],
        [
            434,
            "Elvis Presley - One-Sided Love Affair (1956)"
        ],
        [
            435,
            "Elvis Presley - Tryin' To Get To You (1956)"
        ],
        [
            436,
            "Elvis Presley - Tutti Frutti (1956)"
        ],
        [
            437,
            "Enfance 80.mp4"
        ],
        [
            438,
            "Everything Has Changed ~  Hawkshaw Hawkins (1962) (Country & Western)"
        ],
        [
            439,
            "Falling and Laughing"
        ],
        [
            440,
            "Getting Dizzy ~ The Elegants (1958)"
        ],
        [
            441,
            "Honestly & Truly  ~ Tommy Edwards (1959)"
        ],
        [
            442,
            "I'll String Along With You ~ Don Cherry (1956)"
        ],
        [
            443,
            "Ojala SilVio RodrigueZ"
        ],
        [
            444,
            "Sleepy Time Gal ~ Don Cherry (1956)"
        ],
        [
            445,
            "Soda Stereo - Un misil en mi placard"
        ],
        [
            446,
            "Toto - Africa (Official Video)"
        ],
        [
            447,
            "Travelers All Stars - Dont Give Up (Video Oficial).mp4"
        ],
        [
            448,
            "Ts & Cs.mp4"
        ],
        [
            449,
            "WATERLOO ~ Stonewall Jackson  (1959)"
        ],
        [
            450,
            "Where Are You ~ Frankie Avalon  (1960)"
        ],
        [
            451,
            "esta cobardia julio iglesias.mp4"
        ],
        [
            452,
            "tous les m\u00eames.mp4"
        ],
        [
            453,
            "David Bowie - 'Silly Boy Blue' - 1967"
        ],
        [
            454,
            "Y Nos Dieron Las Diez - Conjunto Primavera.mp4"
        ],
        [
            455,
            "U2  - First TV appearance on RTE 1978"
        ],
        [
            456,
            "U2 - I FALL DOWN - October (1981) HiDef  - - SOTW #141"
        ],
        [
            457,
            "U2 Gloria"
        ],
        [
            458,
            "U2-Fire (October)"
        ],
        [
            459,
            "u2 - stranger in a strange land (audio)"
        ],
        [
            460,
            "Carl Butler-Don't Let Me Cross Over"
        ],
        [
            461,
            "Do The Hansa"
        ],
        [
            462,
            "In a Nutshell"
        ],
        [
            463,
            "Intuition Told Me, Pt. 1"
        ],
        [
            464,
            "Jadore Venise.mp4"
        ],
        [
            465,
            "Japanese Dream"
        ],
        [
            466,
            "Je veux te voir.mp4"
        ],
        [
            467,
            "Johnny Tillotson - Why Do I Love You So (1959).mp4"
        ],
        [
            468,
            "Julio Iglesias  -  Gwendolyne -  Festival de Eurovisi\u00f3n 1970.mp4"
        ],
        [
            469,
            "Julio Iglesias - A Veces Tu A Veces Yo.mp4"
        ],
        [
            470,
            "Julio Iglesias - Un dia tu un dia yo.mp4"
        ],
        [
            471,
            "Just Like Heaven (Dizzy Mix)"
        ],
        [
            472,
            "Just One Kiss"
        ],
        [
            473,
            "Mierda De Ciudad"
        ],
        [
            474,
            "My Darling, My Darling ~ Jaye P. Morgan (1959)"
        ],
        [
            475,
            "Sepultura - Roots Bloody Roots [OFFICIAL VIDEO]"
        ],
        [
            476,
            "Tender Object"
        ],
        [
            477,
            "U2 - I Threw A Brick Trough A Window (album 'October', '81)"
        ],
        [
            478,
            "U2 - Love Is Bigger Than Anything In Its Way.mp4"
        ],
        [
            479,
            "U2 - October 'October' (1981)"
        ],
        [
            480,
            "U2 - Scarlet"
        ],
        [
            481,
            "U2 Is that all WITH LYRIC"
        ],
        [
            482,
            "Untitled Melody"
        ],
        [
            483,
            "Wan Light"
        ],
        [
            484,
            "Gorillaz - 19-2000 (Official Video).mp4"
        ],
        [
            485,
            "Just Say Yes - (Unreleased 2001)"
        ],
        [
            486,
            "L.O.V.E. Love"
        ],
        [
            487,
            "LOS HERMANOS PAJARO alemanes suizos locos ridiculos frikis silbando canci\u00f3n aun mas friki.mp4"
        ],
        [
            488,
            "La piscine.mp4"
        ],
        [
            489,
            "Larme \u00e0 gauche.mp4"
        ],
        [
            490,
            "Les Vitrines.mp4"
        ],
        [
            491,
            "MaRCo ANtonio SoLiS    Resignacion.mp4"
        ],
        [
            492,
            "Marco Antonio Solis - Pirekua Michoacana.mp4"
        ],
        [
            493,
            "Marco Antonio Solis RAZON DE SOBRA.mp4"
        ],
        [
            494,
            "Mr. Pink Eyes"
        ],
        [
            495,
            "New Day"
        ],
        [
            496,
            "Nudes.mp4"
        ],
        [
            497,
            "Ocean"
        ],
        [
            498,
            "U2 - Three  1979 (Full EP).mp4"
        ],
        [
            499,
            "U2 - Tomorrow"
        ],
        [
            500,
            "Vanille fraise.mp4"
        ],
        [
            501,
            "Papalote - Silvio Rodr\u00edguez"
        ],
        [
            502,
            "Plein de bisous.mp4"
        ],
        [
            503,
            "Polo & Pan - Windmills Of Your Mind.1.mp4"
        ],
        [
            504,
            "Poolside - Shakedown Street.mp4"
        ],
        [
            505,
            "Purple Haze (Unreleased)"
        ],
        [
            506,
            "Retiens mon d\u00e9sir.mp4"
        ],
        [
            507,
            "Satellite City"
        ],
        [
            508,
            "Scared As You"
        ],
        [
            509,
            "Signal To Noise (Unreleased 2001)"
        ],
        [
            510,
            "Signal To Noise"
        ],
        [
            511,
            "Velvet Underground and Nico - All Tomorrow's Parties .mp4"
        ],
        [
            512,
            "Velvet Underground-'European Son' from 'Velvet Underground and Nico' LP"
        ],
        [
            513,
            "Velvet Underground-'Heroin' from 'Velvet Underground and Nico' LP"
        ],
        [
            514,
            "Velvet Underground-'I'm Waiting for the Man' w_lyrics from 'Velvet Underground and Nico' LP"
        ],
        [
            515,
            "Velvet Underground-'Run Run Run' from 'Velvet Underground and Nico' LP"
        ],
        [
            516,
            "Los Muertos de Cristo - L\u00e1grimas de Sangre [LETRA]"
        ],
        [
            517,
            "SLAYER - Repentless (OFFICIAL MUSIC VIDEO)"
        ],
        [
            518,
            "Snow In Summer"
        ],
        [
            519,
            "Soy Un Truhan Soy Un Senor - Julio Iglesias.mp4"
        ],
        [
            520,
            "Speak My Language"
        ],
        [
            521,
            "Stop Dead"
        ],
        [
            522,
            "Sugar Girl"
        ],
        [
            523,
            "The Dream"
        ],
        [
            524,
            "The Exploding Boy"
        ],
        [
            525,
            "The Silvertones - Cool Down.mp4"
        ],
        [
            526,
            "The Upstairs Room"
        ],
        [
            527,
            "Three Cheers for Our Side"
        ],
        [
            528,
            "Throw Your Foot"
        ],
        [
            529,
            "Velvet Underground-'Venus in Furs' from 'Velvet Underground and Nico' LP"
        ],
        [
            530,
            "WILL U STILL LOVE ME TOMORROW -THE SHIRELLES (LYRICS).mp4"
        ],
        [
            531,
            "Wake Up"
        ],
        [
            532,
            "Wish You Were Here"
        ],
        [
            533,
            "Without Love - Ken Boothe (Subtitulos Espa\u00f1ol).mp4"
        ],
        [
            534,
            "Agua bendita - A tu lado (letra)"
        ],
        [
            535,
            "U2 - Rejoice (Vinyl, LP)"
        ],
        [
            536,
            "U2 - With a Shout (Jerusalem) [Richard Skinner BBC Live, September 1981]"
        ],
        [
            537,
            "Upwards and Onwards"
        ],
        [
            538,
            "Velvet Underground-'Femme Fatale' from 'Velvet Underground and Nico' LP"
        ],
        [
            539,
            "Velvet Underground-'I'll Be Your Mirror' from 'Velvet Underground and Nico' LP"
        ],
        [
            540,
            "Velvet Underground-'Sunday Morning' from 'Velvet Underground and Nico' LP"
        ],
        [
            541,
            "Velvet Underground-'The Black Angel's Death Song' from 'Velvet Underground and Nico' LP"
        ],
        [
            542,
            "Velvet Underground-'There She Goes Again' from 'Velvet Underground and Nico' LP"
        ],
        [
            543,
            "V\u00e9rit\u00e9.mp4"
        ],
        [
            544,
            "WLT - Golden Silvers - Magic Touch"
        ],
        [
            545,
            "Waiting"
        ],
        [
            546,
            "World In My Eyes"
        ],
        [
            547,
            "Wrong Number (P2p Mix)"
        ],
        [
            548,
            "01Julio Iglesias - De ni\u00f1a a mujer.mp4"
        ],
        [
            549,
            "Julio Iglesias - Me olvid\u00e9 de vivir.mp4"
        ],
        [
            550,
            "03Julio Iglesias - Hey.mp4"
        ],
        [
            551,
            "04Julio Iglesias - Lo mejor de tu vida.mp4"
        ],
        [
            552,
            "BRUJERIA - Don Quijote Marijuana (OFFICIAL MUSIC VIDEO)"
        ],
        [
            553,
            "Julio Iglesias - - Me Va Me Va.mp4"
        ],
        [
            554,
            "Julio Iglesias - Manuela.mp4"
        ],
        [
            555,
            "Julio Iglesias - Me olvid\u00e9 de vivir"
        ],
        [
            556,
            "Julio Iglesias Lo mejor de tu vida"
        ],
        [
            557,
            "Pixies - Dead (Peel Session)"
        ],
        [
            558,
            "CONJUNTO PRIMAVERA luis pulido.mp4"
        ],
        [
            559,
            "Conjunto Primavera - Diganle.mp4"
        ],
        [
            560,
            "Conjunto Primavera - Mi Sacrificio.mp4"
        ],
        [
            561,
            "Conjunto primavera Las Noches Las Hago Dias.mp4"
        ],
        [
            562,
            "Consolation Prize"
        ],
        [
            563,
            "David Bowie - 'Come And Buy My Toys' - 1967"
        ],
        [
            564,
            "David Bowie - 'Join The Gang' - 1967"
        ],
        [
            565,
            "David Bowie - 'Little Bombardier' - 1967"
        ],
        [
            566,
            "David Bowie - 'Love You Till Tuesday' - 1967"
        ],
        [
            567,
            "David Bowie - 'Maid Of Bond Street' - 1967"
        ],
        [
            568,
            "David Bowie - 'Please Mr. Gravedigger' - 1967"
        ],
        [
            569,
            "David Bowie - 'Rubber Band' - 1967"
        ],
        [
            570,
            "David Bowie - 'Sell Me A Coat' - 1967"
        ],
        [
            571,
            "David Bowie - 'She's Got Medals' - 1967"
        ],
        [
            572,
            "Julio Iglesias - Nathalie (Video Oficial) (1982).mp4"
        ],
        [
            573,
            "Julio Iglesias - Ni Te Tengo Ni Te Olvido.mp4"
        ],
        [
            574,
            "Julio Iglesias - No llores mi amor.mp4"
        ],
        [
            575,
            "Stevie Ray Vaughan - Look at Little Sister"
        ],
        [
            576,
            "The Prodigy - Firestarter (Official Video)"
        ],
        [
            577,
            "julio iglesias minueto.mp4"
        ],
        [
            578,
            "Alton Ellis - Get ready for rock reggae steady-z52xN7HrO7I.mp4.part"
        ],
        [
            579,
            "Felicity"
        ],
        [
            580,
            "Filme moi.mp4"
        ],
        [
            581,
            "Frank Sinatra - We Three (My Echo My Shadow And Me) 1940.mp4"
        ],
        [
            582,
            "Gare du Nord.mp4"
        ],
        [
            583,
            "Halo"
        ],
        [
            584,
            "Hano\u00ef caf\u00e9.mp4"
        ],
        [
            585,
            "Happy The Man"
        ],
        [
            586,
            "Hello, I Love You (Slight Return Mix)"
        ],
        [
            587,
            "Hello, I Love You"
        ],
        [
            588,
            "Hey You!!! (Remix)"
        ],
        [
            589,
            "Home"
        ],
        [
            590,
            "I'm Cold"
        ],
        [
            591,
            "Icing Sugar"
        ],
        [
            592,
            "JULIO IGLESIAS - POR EL AMOR DE UNA MUJER   HD.mp4"
        ],
        [
            593,
            "Julio Iglesias - No me vuelvo a enamorar  Clip.mp4"
        ],
        [
            594,
            "Julio Iglesias - Pobre Diablo (DVD Festival De Vi\u00f1a 1981).mp4"
        ],
        [
            595,
            "Julio Iglesias - Preguntale (Videoclip).mp4"
        ],
        [
            596,
            "JULIO IGLESIAS - QUIJOTE (HD 2020).mp4"
        ],
        [
            597,
            "Justice -  We Are Your Friends [HQ Sound]"
        ],
        [
            598,
            "Khruangbin - Evan Finds The Third Room (Official Video)"
        ],
        [
            599,
            "Khruangbin - So We Won't Forget (Official Video)"
        ],
        [
            600,
            "La Familia Iskariote - Hay Ma\u00f1anas Que Es Mejor No Levantarse (Videoclip Oficial)"
        ],
        [
            601,
            "New Order - Bizarre Love Triangle (Official Music Video) [HD Upgrade]"
        ],
        [
            602,
            "Pixies - Debaser (Demo 1)"
        ],
        [
            603,
            "Silvio Rodr\u00edguez - D\u00edas y Flores"
        ],
        [
            604,
            "Kraftwerk Autobahn full.mp4"
        ],
        [
            605,
            "Ruperta"
        ],
        [
            606,
            "Alton Ellis & Tupac - Nothin' Like Rocksteady"
        ],
        [
            607,
            "La Ment"
        ],
        [
            608,
            "La femme \u00e0 la peau bleue.mp4"
        ],
        [
            609,
            "Ladr\u00f3n de Amor - Conjunto Primavera.mp4"
        ],
        [
            610,
            "Laid Back - Tricky Kind Of Thing.mp4"
        ],
        [
            611,
            "Lament (Flexipop Magazine Cover Release)"
        ],
        [
            612,
            "Lenny Kravitz - Let Love Rule (Official Music Video)"
        ],
        [
            613,
            "Nacha Pop    La Chica de Ayer"
        ],
        [
            614,
            "Flippin' In ~ The Virtues (1959)"
        ],
        [
            615,
            "Free Bird Lynyrd Skynyrd - Lyrics"
        ],
        [
            616,
            "I'm Gonna Sit Right Down And Write Myself A Letter ~ Don Cherry (1956)"
        ],
        [
            617,
            "Lenny Kravitz - Low (Official Video)"
        ],
        [
            618,
            "Les filles d\u00e9sir.mp4"
        ],
        [
            619,
            "Lescalier.mp4"
        ],
        [
            620,
            "Let It Be (Remastered 2009)"
        ],
        [
            621,
            "Level 42 - Lessons In Love (Extended Video)"
        ],
        [
            622,
            "Lovin' Tree ~ Larry Hall (1959)"
        ],
        [
            623,
            "Sin Dios -  Ingobernables"
        ],
        [
            624,
            "Slayer - Seasons In The Abyss (Official Video)"
        ],
        [
            625,
            "Stonewall Jackson-Smoke Along The Track"
        ],
        [
            626,
            "The Twenty Second Day ~ The Diamonds (1959)"
        ],
        [
            627,
            "Victimas del Doctor Cerebro - Ya Tus Amigos"
        ],
        [
            628,
            "L'Imp\u00e9ratrice \u2664 L\u00c0-HAUT"
        ],
        [
            629,
            "LImp\u00e9ratrice \u2014 SONATE PACIFIQUE.mp4"
        ],
        [
            630,
            "LImp\u00e9ratrice \u2654 LImp\u00e9ratrice.mp4"
        ],
        [
            631,
            "La Ley - Aqu\u00ed (Video Oficial)"
        ],
        [
            632,
            "Blue Doll ~ Anita Carter  (1957)"
        ],
        [
            633,
            "Heroe de Leyenda Heroes del silencio"
        ],
        [
            634,
            "I Didn't Know About You ~ Don Cherry (1956)"
        ],
        [
            635,
            "It's All Over ~ Otis Williams & His Charms (1956)"
        ],
        [
            636,
            "L'Imp\u00e9ratrice \u2657 VANILLE FRAISE(2).mp4"
        ],
        [
            637,
            "Little Star ~ The Elegants (1958)"
        ],
        [
            638,
            "Miss The Love (That I've Been Dreaming Of) ~ Otis Williams & His New Group (1955)"
        ],
        [
            639,
            "My Future Just Passed ~ Don Cherry (1956)"
        ],
        [
            640,
            "Piperrak - Mi primer amor"
        ],
        [
            641,
            "Poolside - Shakedown Street"
        ],
        [
            642,
            "Save Me, Save Me ~ Otis Williams & His New Group (1955)"
        ],
        [
            643,
            "The Tear Of The Year ~ Jackie Wilson (1960)"
        ],
        [
            644,
            "Without A Song ~ The Gaylords  (1955)"
        ],
        [
            645,
            "Jos\u00e9 Jos\u00e9 - Agua Con Sal (Cover Audio)"
        ],
        [
            646,
            "King Diamond - Sleepless Nights [OFFICIAL VIDEO]"
        ],
        [
            647,
            "LImp\u00e9ratrice \u2657 VANILLE FRAISE.mp4"
        ],
        [
            648,
            "Pixies - Debaser (Demo 2)"
        ],
        [
            649,
            "The Chemical Brothers - Wide Open ft Beck [8D AUDIO].mp4"
        ],
        [
            650,
            "EL AMOR - JULIO IGLESIAS.mp4"
        ],
        [
            651,
            "Eskorbuto - Ya no quedan m\u00e1s cojones, Eskorbuto a las elecciones (Full Album _ \u00c1lbum completo)"
        ],
        [
            652,
            "Gary Moore - Parisienne Walkways - Live HD"
        ],
        [
            653,
            "King Diamond - The Family Ghost [OFFICIAL VIDEO]"
        ],
        [
            654,
            "LUNIZ -- I GOT 5 ON IT.mp4"
        ],
        [
            655,
            "Lollypop Lorry - I Wont Let You Go (live at Octopus 8052016).mp4"
        ],
        [
            656,
            "Long Gone Day"
        ],
        [
            657,
            "Lord Echo - Thinking Of You (Edit).mp4"
        ],
        [
            658,
            "Love Will Keep Us Together.mp4"
        ],
        [
            659,
            "The Beatles - Here Comes The Sun (2019 Mix)"
        ],
        [
            660,
            "Ciudad de la Furia - Soda Stereo (Andrea Echeverri) Unplugged"
        ],
        [
            661,
            "Eskorbuto - Historia Triste (Audio Oficial)"
        ],
        [
            662,
            "LyricsBreaking Up Is Hard To Do-Neil Sedaka.mp4"
        ],
        [
            663,
            "Marco Antonio Sol\u00eds - Donde Estara Mi Primavera.mp4"
        ],
        [
            664,
            "Marco Antonio Sol\u00c3\u0192\u00c2\u00ads - El Masoquista.mp4"
        ],
        [
            665,
            "Marco Antonio Sol\u00eds - Amor En Silencio.mp4"
        ],
        [
            666,
            "Marco Antonio Sol\u00eds - \u00bfA D\u00f3nde Vamos A Parar.mp4"
        ],
        [
            667,
            "Ser Fuertes"
        ],
        [
            668,
            "Marco Antonio Sol\u00eds - Antes De Que Te Vayas.mp4"
        ],
        [
            669,
            "Marco Antonio Sol\u00eds - Casas De Cart\u00f3n.mp4"
        ],
        [
            670,
            "Silvio Rodr\u00edguez - El dia feliz que est\u00e1 llegando"
        ],
        [
            671,
            "marco antonio solis de haber sabido.mp4"
        ],
        [
            672,
            "Apocalyptica - 'Seemann' feat. Nina Hagen (Official Video) (Rammstein Cover)"
        ],
        [
            673,
            "El Ultimo Ska"
        ],
        [
            674,
            "Faltos de riego - Hoy es mi dia"
        ],
        [
            675,
            "MARCO ANTONIO SOLIS - HAY DE AMORES A AMORES   (2010).mp4"
        ],
        [
            676,
            "Marco antonio solis- en chile-Tu hombre perfecto.mp4"
        ],
        [
            677,
            "Marco antonio solis-Dios bendiga nuestro amor.mp4"
        ],
        [
            678,
            "Simple Man - Lynyrd Skynyrd - Lyrics HD"
        ],
        [
            679,
            "Alice In Chains - Man in the Box (Official Video).mp4"
        ],
        [
            680,
            "MARCO ANTONIO SOLIS LAS NOCHES LAS HAGO DIAS.mp4"
        ],
        [
            681,
            "Marco Antonio Solis - Hay veces.mp4"
        ],
        [
            682,
            "Marco Antonio Solis- Himno a la Humildad.mp4"
        ],
        [
            683,
            "Marco Antonio Sol\u00eds - La Venia Bendita.mp4"
        ],
        [
            684,
            "Marco Antonio Sol\u00eds - Me Vas A Hacer Llorar.mp4"
        ],
        [
            685,
            "Parcels ~ Overnight.mp4"
        ],
        [
            686,
            "Manu Chao - Me llaman calle"
        ],
        [
            687,
            "Marco Antonio Solis - Mujeres Solitas.mp4"
        ],
        [
            688,
            "Marco Antonio Sol\u00eds - Mi Mayor Sacrificio.mp4"
        ],
        [
            689,
            "Marco Antonio Sol\u00eds "
        ],
        [
            690,
            "Marco Antonio Sol\u00eds - Muevete.mp4"
        ],
        [
            691,
            "Parcels ~ Gamesofluck.mp4"
        ],
        [
            692,
            "Primus - Jerry Was A Race Car Driver"
        ],
        [
            693,
            "blink-182 - Man Overboard (Official Video)"
        ],
        [
            694,
            "Hoy es mi d\u00eda (Kaos Etiliko). COVER"
        ],
        [
            695,
            "Marco Antonio Sol\u00eds - M\ufffds Que Tu Amigo.mp4"
        ],
        [
            696,
            "Marco Antonio Sol\u00eds - No Molestar (Concept Video).mp4"
        ],
        [
            697,
            "Marco Antonio Sol\u00eds - No Puedo Olvidarla.mp4"
        ],
        [
            698,
            "First Date ~ Nelson Ray (1958)"
        ],
        [
            699,
            "Guitar Boogie Shuffle ~ The Virtues (1959)"
        ],
        [
            700,
            "Guitar In Orbit ~ The Virtues (1959)"
        ],
        [
            701,
            "Jumpin' Jack ~ The Kalin Twins (1958)"
        ],
        [
            702,
            "Marco Antonio Sol\u00eds - O Me Voy O Te Vas.mp4"
        ],
        [
            703,
            "Marco Antonio Sol\u00eds - Ojal\u00e1.mp4"
        ],
        [
            704,
            "Marco Antonio Sol\u00eds Pasion Vega - Como Tu Mujer.mp4"
        ],
        [
            705,
            "My Love ~ Marty Robbins (1960)"
        ],
        [
            706,
            "Sinergia - Jefe (Video Oficial)"
        ],
        [
            707,
            "Antonio Vega - Chica De Ayer"
        ],
        [
            708,
            "David Bowie - Starman"
        ],
        [
            709,
            "MARCO ANTONIO SOLIS - Se va muriendo mi alma.mp4"
        ],
        [
            710,
            "Marco Antonio Solis - Siempre tu a mi lado.mp4"
        ],
        [
            711,
            "Marco Antonio Sol\u00eds - Recuerdos Tristeza Y Soledad.mp4"
        ],
        [
            712,
            "Marco Antonio Sol\u00eds - Sigue Sin Mi.mp4"
        ],
        [
            713,
            "(It Took) One Kiss ~ Jaye P  Morgan (1959)"
        ],
        [
            714,
            "A Million To One ~ The Five Satins (1958)"
        ],
        [
            715,
            "At My Front Door ~ The El Dorados (1955)"
        ],
        [
            716,
            "Green Day - Good Riddance (Time Of Your Life) [Official Music Video]"
        ],
        [
            717,
            "Gum Drop ~ Otis Williams & His New Group (1955)"
        ],
        [
            718,
            "I Can't Forget (You) ~ Patsy Cline (1962) (Country & Western)"
        ],
        [
            719,
            "I Don't Wanta ~ Patsy Cline (1962) (Country & Western)"
        ],
        [
            720,
            "I'm Yours ~ Don Cherry  (1956)"
        ],
        [
            721,
            "Over The Mountain, Across The Sea ~ Johnnie & Joe (1957)(78 rpm)"
        ],
        [
            722,
            "Skid Row - I Remember You (Official Music Video)"
        ],
        [
            723,
            "Speedin' ~ The Medallions (1955)(78 rpm)"
        ],
        [
            724,
            "Tell Me Now ~ Otis Williams & His New Group (1955)"
        ],
        [
            725,
            "The Cure (extended) To The Sky.mp4"
        ],
        [
            726,
            "Dire Straits - Sultans Of Swing"
        ],
        [
            727,
            "Marco Antonio Sol\u00eds - Si Me Puedo Quedar.mp4"
        ],
        [
            728,
            "Marco Antonio Sol\u00eds - Si No Te Hubieras Ido (Live).mp4"
        ],
        [
            729,
            "Marco Antonio Sol\u00eds - Sin Lado Izquierdo.mp4"
        ],
        [
            730,
            "My Morning Jacket - Just One Thing"
        ],
        [
            731,
            "The Chemical Brothers - Get Yourself High.mp4"
        ],
        [
            732,
            "The Velvet Underground - After Hours"
        ],
        [
            733,
            "blink-182 - I Miss You (Official Video)"
        ],
        [
            734,
            "murio mi padre conjunto primavera.mp4"
        ],
        [
            735,
            "Marco Antonio Sol\u00eds - Si Te Pudiera Mentir.mp4"
        ],
        [
            736,
            "Marco Antonio Sol\u00eds - Tu Carcel.mp4"
        ],
        [
            737,
            "H\u00e9roes Del Silencio - Agosto (HQ)"
        ],
        [
            738,
            "MARCO ANTONIO SOLISUN PAR DE HUMANOSMARTHA MILAGROS GARIBAY  GARIBAY LAS ZARQUILLAS MICHOACAN.mp4"
        ],
        [
            739,
            "Marco Antonio Solis T\u00fa otra vez.mp4"
        ],
        [
            740,
            "Marco Antonio Sol\u00eds - Tu Me Vuelves Loco.mp4"
        ],
        [
            741,
            "Rage Against The Machine - Killing In the Name (Official Music Video)"
        ],
        [
            742,
            "The Strokes - Someday (Official Music Video)"
        ],
        [
            743,
            "Marco Antonio Sol\u00eds - Tu Amor O Tu Desprecio.mp4"
        ],
        [
            744,
            "Maybe Someday (Acoustic Mix)"
        ],
        [
            745,
            "Pearl Jam"
        ],
        [
            746,
            "ELLA ERA UN TRAVESTI - VILMA PALMA E VAMPIROS"
        ],
        [
            747,
            "Eric Clapton - I Shot The Sheriff [Crossroads 2010] (Official Live Video)"
        ],
        [
            748,
            "Mi eterno amor secreto - Marco Antonio Solis.mp4"
        ],
        [
            749,
            "Miami Nights 1984 - Early Summer.mp4"
        ],
        [
            750,
            "Gustavo Cerati \"Adi\u00f3s\" (Official Video).mp4"
        ],
        [
            751,
            "Mojo.mp4"
        ],
        [
            752,
            "Silvio Rodr\u00edguez - Oleo De Una Mujer Con Sombrero [HD]"
        ],
        [
            753,
            "BRUJERIA - La Ley De Plomo (OFFICIAL MUSIC VIDEO)"
        ],
        [
            754,
            "Joy Division - Love Will Tear Us Apart [OFFICIAL MUSIC VIDEO]"
        ],
        [
            755,
            "Molchat Doma - Kletka (Official Lyrics Video) \u041c\u043e\u043b\u0447\u0430\u0442 \u0414\u043e\u043c\u0430 - \u041a\u043b\u0435\u0442\u043a\u0430.mp4"
        ],
        [
            756,
            "More Than This (From The X-Files - The Album)"
        ],
        [
            757,
            "Nada"
        ],
        [
            758,
            "Narciso Yepes (Romance Anonimo).mp4"
        ],
        [
            759,
            "black midi - bmbmbm (Live on KEXP)"
        ],
        [
            760,
            "FOALS - Exits [Official Music Video].mp4"
        ],
        [
            761,
            "IDLES - MOTHER (Official Video)"
        ],
        [
            762,
            "John Lennon - Imagine - Lyrics"
        ],
        [
            763,
            "La Polla Records - Y ahora que"
        ],
        [
            764,
            "NEWCLEUS - JAM ON IT.mp4"
        ],
        [
            765,
            "Alton Ellis - Rocksteady"
        ],
        [
            766,
            "Night Flight (Live).mp4"
        ],
        [
            767,
            "Nutshell"
        ],
        [
            768,
            "Oasis - Wonderwall  (Official Video)"
        ],
        [
            769,
            "Orange Juice -  Rip It Up (Official Video)"
        ],
        [
            770,
            "The Specials - A Message To You Rudy (Official Music Video)"
        ],
        [
            771,
            "A Fallen Star ~ Jimmy Newman (1957) (Country & Western)"
        ],
        [
            772,
            "Bless You ~ Clyde McPhatter (1959)"
        ],
        [
            773,
            "Caifanes - La Negra Tomasa"
        ],
        [
            774,
            "Don't Let Love Pass Me By ~ Frankie Avalon  (1960)"
        ],
        [
            775,
            "Fatboy Slim - Weapon Of Choice [Official Video]"
        ],
        [
            776,
            "I Can't Go On This Way ~ Jimmy Newman (1957) (Country & Western)"
        ],
        [
            777,
            "John Lennon - No 9 Dream"
        ],
        [
            778,
            "Manu Chao - Clandestino (Full Album)"
        ],
        [
            779,
            "Nina Hagen - African Reggae"
        ],
        [
            780,
            "Out Of This World (Unreleased 2000)"
        ],
        [
            781,
            "Over Now"
        ],
        [
            782,
            "Pachanga Boys - Time.mp4"
        ],
        [
            783,
            "Please Be Kind ~ Don Cherry (1956)"
        ],
        [
            784,
            "A Wasted Love Affair ~ Goldie Hill (1957) (Country & Western)"
        ],
        [
            785,
            "Cleanin' House ~ Goldie Hill (1957) (Country & Western)"
        ],
        [
            786,
            "Dream Of The Year ~ Jimmy Elledge (1964) (w_echo)"
        ],
        [
            787,
            "Falling In Love ~ Warner Mack (1958) (C & W - Rockabilly)"
        ],
        [
            788,
            "I'm Coming Home ~ Johnny Horton  (1956)"
        ],
        [
            789,
            "In Care Of The Blues ~ Patsy Cline (1964) (Country & Western)"
        ],
        [
            790,
            "Is There Something On Your Mind ~ Jack Scott (1961)"
        ],
        [
            791,
            "Joy Division - Transmission [OFFICIAL MUSIC VIDEO]"
        ],
        [
            792,
            "Let The Tears Begin ~ Johnny Bond (1963) (Country & Western)"
        ],
        [
            793,
            "MAX MIX 2 (Megamix Version) -1985 - Original Master Reel.mp4"
        ],
        [
            794,
            "My Girl ~ The Eternals (1959)"
        ],
        [
            795,
            "The Biggest Break ~ Bob Gallion (1964) (Country & Western)"
        ],
        [
            796,
            "Auto Rojo - Vilma Palma e Vampiros (Video Oficial)"
        ],
        [
            797,
            "Exit"
        ],
        [
            798,
            "Julio Iglesias - Lo mejor de tu vida.mp4"
        ],
        [
            799,
            "Para\u00edso - Teu Sorriso (Jex Opolis Remix).mp4"
        ],
        [
            800,
            "Pixies  - - Debaser"
        ],
        [
            801,
            "POR EL BIEN DE LOS DOS - CONJUNTO PRIMAVERA.mp4"
        ],
        [
            802,
            "Silversun Pickups - Lazy Eye (Official Video).mp4"
        ],
        [
            803,
            "The Cure - Halo with lyrics and subs.mp4"
        ],
        [
            804,
            "The Good Life - Lovers Need Lawyers [Official Music Video].mp4"
        ],
        [
            805,
            "John Lennon-Woman (Lyrics)"
        ],
        [
            806,
            "Para Vivir Sin Ti-Marco Antonio Solis-2010.mp4"
        ],
        [
            807,
            "Parlour Magic - 'Phantom West' (OFFICIAL AUDIO)"
        ],
        [
            808,
            "Pasteur Lappe - Na Real Sekele Fo Ya.mp4"
        ],
        [
            809,
            "Pasteur Lappe - The Sekele Movement.mp4"
        ],
        [
            810,
            "Paul Simon - Diamonds On The Soles Of Her Shoes (Todd Terje Edit).mp4"
        ],
        [
            811,
            "Peter Brown - Dance With Me 1978.mp4"
        ],
        [
            812,
            "Phil Collins - Another Day In Paradise (Official Music Video)"
        ],
        [
            813,
            "Play"
        ],
        [
            814,
            "Polo .mp4"
        ],
        [
            815,
            "The Rasmus - In The Shadows (US Version)"
        ],
        [
            816,
            "pobre de mi corazonconjunto primavera.mp4"
        ],
        [
            817,
            "Fito y Fitipaldis - 09 Ojos de Serpiente.mp4"
        ],
        [
            818,
            "AFI - Silver And Cold (Official Music Video).mp4"
        ],
        [
            819,
            "Quiero estar loco - Conjunto Primavera.mp4"
        ],
        [
            820,
            "Possession (Unreleased 2000)"
        ],
        [
            821,
            "Purple Haze (From Stone Free - A Tribute To Jimi Hendrix)"
        ],
        [
            822,
            "RIP + Eskorbuto \u200e\u2013 Zona Especial Norte (Full split 1984)"
        ],
        [
            823,
            "presiento que voy a llorar (MARCO ANTONIO SOLIS).mp4"
        ],
        [
            824,
            "Cafe Tacvba - Las Flores (MTV Unplugged) (HD)"
        ],
        [
            825,
            "Que te quieran mas que yo-Marco Antonio Solis.mp4"
        ],
        [
            826,
            "Radiohead - Creep"
        ],
        [
            827,
            "Ray Conniff and Julio Iglesias Hey!.mp4"
        ],
        [
            828,
            "The Cranberries - Dreams (Official Music Video)"
        ],
        [
            829,
            "blink-182 - Josie (Official Video)"
        ],
        [
            830,
            "Heroes Del Silencio - La Lluvia Gris (HQ)"
        ],
        [
            831,
            "Recto Verso.mp4"
        ],
        [
            832,
            "Red Hot Chili Peppers - Scar Tissue [Official Music Video]"
        ],
        [
            833,
            "Release"
        ],
        [
            834,
            "The Cranberries - Ode To My Family (Official Music Video)"
        ],
        [
            835,
            "Vilma Palma e Vampiros - La pachanga (1992)"
        ],
        [
            836,
            "RETROMIXLEVEL42ERASUREPSB httpssoundcloudcomramiro-miranda-961836593my-megamix-big-late-80s.mp4"
        ],
        [
            837,
            "Roi.mp4"
        ],
        [
            838,
            "Rotten Apple"
        ],
        [
            839,
            "Ska-P - El Olvidado"
        ],
        [
            840,
            "Slayer - Raining Blood"
        ],
        [
            841,
            "Breezin' ~ Eddie Beal Combo  (1957)"
        ],
        [
            842,
            "Haruomi Hosono - Sports Men"
        ],
        [
            843,
            "Johnny Sorrow ~ Les 'Carrot Top' Anderson (1958) (Country & Western)"
        ],
        [
            844,
            "Knocked Out ~ Ernie Fields & His Orchestra (1960)"
        ],
        [
            845,
            "Mr.  Lonely ~ Bobby VInton (1964)"
        ],
        [
            846,
            "Playboy, Page Fourteen ~ Leon McAuliffe (1965)"
        ],
        [
            847,
            "Skinshape-Life & Love.mp4"
        ],
        [
            848,
            "The Cranberries - Promises (Official Music Video)"
        ],
        [
            849,
            "The Last Dance ~ Don Cherry (1957)"
        ],
        [
            850,
            "W-P-L-J ~ The 4 Deuces (1955)(78 rpm)"
        ],
        [
            851,
            "Who Can Explain  ~ Frankie Lymon & The Teenagers (1956)(78 rpm)"
        ],
        [
            852,
            "Who Knows ~ The Charms (1954)(78 rpm)"
        ],
        [
            853,
            "silvio rodriguez OJALA"
        ],
        [
            854,
            "Limp Bizkit - Break Stuff"
        ],
        [
            855,
            "Soundgarden - Fell On Black Days"
        ],
        [
            856,
            "Splintered In Her Head"
        ],
        [
            857,
            "Stone Temple Pilots - Creep (Official Music Video)"
        ],
        [
            858,
            "Stone Temple Pilots - Interstate Love Song (Official HD Music Video)"
        ],
        [
            859,
            "04 - Kortatu - Sarri Sarri"
        ],
        [
            860,
            "Caifanes - Para Que No Digas Que No Pienso En Ti"
        ],
        [
            861,
            "Comin' Down With Love ~ Mel Gadson (1960)"
        ],
        [
            862,
            "I'm Gettin' Sentimental Over You ~ Mel Gadson (1960)"
        ],
        [
            863,
            "It ~ The Gaylords (1955)"
        ],
        [
            864,
            "OH LONESOME ME ~ Don Gibson  1958.wmv"
        ],
        [
            865,
            "Swimming Tapes - Morningside [Full Album].mp4"
        ],
        [
            866,
            "The Cranberries - Linger (Official Music Video)"
        ],
        [
            867,
            "Vilma Palma e Vampiros - Mojada"
        ],
        [
            868,
            "When The Sun Comes Out ~ Don Cherry  (1956)"
        ]
    ]
}